{"type":"FeatureCollection","features":[{"type":"Feature","properties":{"id":1,"name":"Barcelona","image":"barcelona_image"},"geometry":{"coordinates":[2.1768703043360915,41.38247453990883],"type":"Point"}},{"type":"Feature","properties":{"id":2,"name":"Lleida","image":"lleida_image"},"geometry":{"coordinates":[0.6252174915418607,41.617177265238325],"type":"Point"}},{"type":"Feature","properties":{"id":3,"name":"Girona","image":"girona_image"},"geometry":{"coordinates":[2.827955994409848,41.97781425995976],"type":"Point"}},{"type":"Feature","properties":{"id":4,"name":"Tarragona","image":"tarragona_image"},"geometry":{"coordinates":[1.2580484426421776,41.121715323657384],"type":"Point"}}]}